kabbes_pypi_builder/CONFIG.json
kabbes_pypi_builder/Client.py
kabbes_pypi_builder/PackageGenerator.py
kabbes_pypi_builder/__init__.py
kabbes_pypi_builder/__main__.py
kabbes_pypi_builder/Templates/default/LICENSE
kabbes_pypi_builder/Templates/default/pyproject.toml
kabbes_pypi_builder/Templates/default/requirements.txt
kabbes_pypi_builder/Templates/default/setup.cfg
kabbes_pypi_builder/Templates/default/setup.py
kabbes_pypi_builder/Templates/default/{-{src_name}-}/{-{package_name}-}/CONFIG.json
kabbes_pypi_builder/Templates/default/{-{src_name}-}/{-{package_name}-}/__init__.py
kabbes_pypi_builder/Templates/default/{-{src_name}-}/{-{package_name}-}/__main__.py
kabbes_pypi_builder-0.11.0.dist-info/LICENSE
kabbes_pypi_builder-0.11.0.dist-info/METADATA
kabbes_pypi_builder-0.11.0.dist-info/WHEEL
kabbes_pypi_builder-0.11.0.dist-info/top_level.txt
kabbes_pypi_builder-0.11.0.dist-info/RECORD
