Metadata-Version: 2.1
Name: kabbes-pypi-builder
Version: 0.11.0
Summary: project for easily deploying code to Python Package Index
Home-page: https://pypi.org/project/kabbes-pypi-builder
Author: James Kabbes
Author-email: james.kabbes@gmail.com
Project-URL: GitHub, https://github.com/jameskabbes/pypi_builder
Project-URL: Documentation, https://jameskabbes.github.io/pypi_builder
Classifier: Programming Language :: Python :: 3
Classifier: License :: OSI Approved :: MIT License
Classifier: Operating System :: OS Independent
Requires-Python: >=3.7
License-File: LICENSE
Requires-Dist: kabbes-py-starter
Requires-Dist: kabbes-parent-class
Requires-Dist: kabbes-dir-ops
Requires-Dist: kabbes-repository-generator
